tune8/__init__.py
tune8/app.py
tune8/default_system.txt
tune8/prompts.jsonl
tune8/__pycache__/__init__.cpython-310.pyc
tune8/__pycache__/app.cpython-310.pyc
tune8/static/css/style.css
tune8/templates/index.html
tune8-0.1.0.dist-info/LICENSE
tune8-0.1.0.dist-info/METADATA
tune8-0.1.0.dist-info/WHEEL
tune8-0.1.0.dist-info/entry_points.txt
tune8-0.1.0.dist-info/top_level.txt
tune8-0.1.0.dist-info/RECORD
