Metadata-Version: 2.1
Name: tune8
Version: 0.1.0
Summary: A dashboard to work with Fine-tune JSONL
Home-page: https://github.com/naserjamal/tune8
Author: Naser Jamal
Author-email: naser.dll@hotmail.com
License: UNKNOWN
Platform: UNKNOWN
Classifier: Programming Language :: Python :: 3
Classifier: License :: OSI Approved :: MIT License
Classifier: Operating System :: OS Independent
License-File: LICENSE
Requires-Dist: Flask
